README.md
setup.py
cdApi/__init__.py
cdApi/auth.py
cdApi/base.py
cdApi/coupon.py
cdApi/coupon_pack.py
cdApi/discount.py
cdApi/home.py
cdApi/live.py
cdApi/material.py
cdApi/order.py
cdApi/product.py
cdApi/store.py
cdApi/store_product.py
cdApi/task.py
cdApi/token_api.py
cdApi/user.py
cd_api.egg-info/PKG-INFO
cd_api.egg-info/SOURCES.txt
cd_api.egg-info/dependency_links.txt
cd_api.egg-info/requires.txt
cd_api.egg-info/top_level.txt
wowkai_open_api/__init__.py
wowkai_open_api/api.py
wowkai_open_api/base.py
wowkai_open_api/coupon.py
wowkai_open_api/joeone.py
wowkai_open_api/logistics.py
wowkai_open_api/order.py
wowkai_open_api/token_api.py