Metadata-Version: 1.0
Name: cd-api
Version: 1.1.19
Summary: 任秋锴的草动工具箱
Home-page: http://git.renqiukai.com:1983/renqiukai/rqk-cd-tools.git
Author: Renqiukai
Author-email: renqiukai@qq.com
License: MIT Licence
Keywords: cdApi,cd,rqk
Platform: any
